{
  "web": {
    "client_id": "413144330174-f2qk1irsptb4jt5j55j82mpe6n0ffd14.apps.googleusercontent.com",
    "project_id": "musik-368920",
    "auth_uri": "https://accounts.google.com/o/oauth2/auth",
    "token_uri": "https://oauth2.googleapis.com/token",
    "auth_provider_x509_cert_url": "https://www.googleapis.com/oauth2/v1/certs",
    "client_secret": "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",
    "redirect_uris": ["http://localhost:3000/","http://localhost:3000/?ggCallback","https://kuntzeprojects-musik.netlify.app/?ggCallback"],
    "javascript_origins": ["http://localhost:3000"]
  }
}
